huobi/__init__.py
huobi/requstclient.py
huobi/subscriptionclient.py
huobi/base/__init__.py
huobi/base/printobject.py
huobi/base/printtime.py
huobi/constant/__init__.py
huobi/constant/result.py
huobi/constant/system.py
huobi/constant/test.py
huobi/demo_service/__init__.py
huobi/demo_service/mbp/__init__.py
huobi/demo_service/mbp/mbp_data_process.py
huobi/demo_service/mbp/mbp_print.py
huobi/exception/__init__.py
huobi/exception/huobiapiexception.py
huobi/impl/__init__.py
huobi/impl/accountinfomap.py
huobi/impl/restapiinvoker.py
huobi/impl/restapirequest.py
huobi/impl/restapirequestimpl.py
huobi/impl/websocketconnection.py
huobi/impl/websocketrequest.py
huobi/impl/websocketrequestimpl.py
huobi/impl/websocketrequestimplv2.py
huobi/impl/websocketwatchdog.py
huobi/impl/utils/__init__.py
huobi/impl/utils/apisignature.py
huobi/impl/utils/apisignaturev2.py
huobi/impl/utils/channelparser.py
huobi/impl/utils/channels.py
huobi/impl/utils/channelsrequest.py
huobi/impl/utils/etfresult.py
huobi/impl/utils/inputchecker.py
huobi/impl/utils/jsonwrapper.py
huobi/impl/utils/timeservice.py
huobi/impl/utils/urlparamsbuilder.py
huobi/model/__init__.py
huobi/model/account.py
huobi/model/accountbalancerequest.py
huobi/model/accountchange.py
huobi/model/accountevent.py
huobi/model/accounthistory.py
huobi/model/accountsupdate.py
huobi/model/accountsupdateevent.py
huobi/model/balance.py
huobi/model/batchcancelresult.py
huobi/model/bestquote.py
huobi/model/candlestick.py
huobi/model/candlestickevent.py
huobi/model/candlestickrequest.py
huobi/model/chain.py
huobi/model/chaindepositaddress.py
huobi/model/completesubaccountinfo.py
huobi/model/constant.py
huobi/model/crossmarginaccountbalance.py
huobi/model/deposit.py
huobi/model/depthentry.py
huobi/model/etfswapconfig.py
huobi/model/etfswaphistory.py
huobi/model/exchangeinfo.py
huobi/model/feerate.py
huobi/model/lasttradeandbestquote.py
huobi/model/loan.py
huobi/model/loanorder.py
huobi/model/marginbalancedetail.py
huobi/model/matchresult.py
ahrli_huobi_client-1.0.8.dist-info/LICENSE
ahrli_huobi_client-1.0.8.dist-info/METADATA
ahrli_huobi_client-1.0.8.dist-info/WHEEL
ahrli_huobi_client-1.0.8.dist-info/top_level.txt
ahrli_huobi_client-1.0.8.dist-info/RECORD
