Metadata-Version: 2.1
Name: ahrli-huobi-client
Version: 1.0.8
Summary: UNKNOWN
Home-page: UNKNOWN
Author: UNKNOWN
Author-email: UNKNOWN
License: UNKNOWN
Platform: UNKNOWN
Requires-Dist: requests
Requires-Dist: apscheduler
Requires-Dist: websocket-client
Requires-Dist: urllib3
